ezrules/__init__.py
ezrules/cli.py
ezrules/settings.py
ezrules/backend/data_utils.py
ezrules/backend/ezruleapp.py
ezrules/backend/ezrulevalapp.py
ezrules/backend/forms.py
ezrules/backend/tasks.py
ezrules/backend/utils.py
ezrules/backend/rule_executors/executors.py
ezrules/backend/static/scripts.js
ezrules/backend/templates/create_rule.html
ezrules/backend/templates/layout.html
ezrules/backend/templates/outcomes.html
ezrules/backend/templates/rules.html
ezrules/backend/templates/show_rule.html
ezrules/backend/templates/timeline.html
ezrules/backend/templates/user_header.html
ezrules/backend/templates/user_lists.html
ezrules/core/outcomes.py
ezrules/core/rule.py
ezrules/core/rule_checkers.py
ezrules/core/rule_engine.py
ezrules/core/rule_helpers.py
ezrules/core/rule_updater.py
ezrules/core/user_lists.py
ezrules/models/backend_core.py
ezrules/models/database.py
ezrules/models/history_meta.py
ezrules-0.8.0.dist-info/METADATA
ezrules-0.8.0.dist-info/WHEEL
ezrules-0.8.0.dist-info/entry_points.txt
ezrules-0.8.0.dist-info/licenses/LICENSE
ezrules-0.8.0.dist-info/RECORD
